epsonprinter_pkg/__init__.py
epsonprinter_pkg/epsonprinterapi.py
epsonprinter-0.0.9.dist-info/LICENSE
epsonprinter-0.0.9.dist-info/METADATA
epsonprinter-0.0.9.dist-info/WHEEL
epsonprinter-0.0.9.dist-info/top_level.txt
epsonprinter-0.0.9.dist-info/RECORD
