Metadata-Version: 2.1
Name: epsonprinter
Version: 0.0.9
Summary: Communication package for Epson Workforce printer
Home-page: https://github.com/thastealth/epsonprinter
Author: ThaStealth
Author-email: author@example.com
License: UNKNOWN
Platform: UNKNOWN
Classifier: Programming Language :: Python :: 3
Classifier: License :: OSI Approved :: MIT License
Classifier: Operating System :: OS Independent
